axologgle/__init__.py
axologgle/axologgle.py
axologgle-1.0.2.dist-info/LICENSE
axologgle-1.0.2.dist-info/METADATA
axologgle-1.0.2.dist-info/WHEEL
axologgle-1.0.2.dist-info/top_level.txt
axologgle-1.0.2.dist-info/RECORD
