Metadata-Version: 2.1
Name: axologgle
Version: 1.0.2
Summary: Logging tools but cooler
Home-page: https://github.com/LiterallyAxo/AxoLoggle
Author: Axo
Author-email: axo@itsaxo.lol
License: MIT
Platform: UNKNOWN
Classifier: Programming Language :: Python :: 3
Classifier: License :: OSI Approved :: MIT License
Classifier: Operating System :: OS Independent
Requires-Python: >=3.10
License-File: LICENSE
Requires-Dist: colorama
